[
  {
    "name": "Little Star Cake",
    "url": "https://www.bakerdays.com/little-star-gift-set"
  },
  {
    "name": "Clever Sausage Cake",
    "url": "https://www.bakerdays.com/clever-sausage-cake"
  },
  {
    "name": "Fearless King Cake",
    "url": "https://www.bakerdays.com/fearless-king-cake"
  },
  {
    "name": "Yas Queen Cake",
    "url": "https://www.bakerdays.com/yas-queen-cake"
  },
  {
    "name": "Tiered Champagne Congrats Cake",
    "url": "https://www.bakerdays.com/tiered-champagne-congrats-cake"
  },
  {
    "name": "Sip, Sip, Hooray Cake",
    "url": "https://www.bakerdays.com/sip-sip-hooray-cake"
  },
  {
    "name": "Rainbow Congrats Cake",
    "url": "https://www.bakerdays.com/rainbow-congrats-cake"
  },
  {
    "name": "Be Safe Stay Strong Cake",
    "url": "https://www.bakerdays.com/be-safe-stay-strong-cake"
  },
  {
    "name": "You CAN Cake",
    "url": "https://www.bakerdays.com/you-can-cake"
  },
  {
    "name": "Rainbow Dream Cake",
    "url": "https://www.bakerdays.com/rainbow-dream-cake"
  },
  {
    "name": "Yes! You Can Cake",
    "url": "https://www.bakerdays.com/yes-you-can-cake"
  },
  {
    "name": "Bee Happy Cake",
    "url": "https://www.bakerdays.com/bee-happy-cake"
  },
  {
    "name": "Stronger Cake",
    "url": "https://www.bakerdays.com/stronger-cake"
  },
  {
    "name": "Thinking Hearts Cake",
    "url": "https://www.bakerdays.com/thinking-hearts-cake"
  },
  {
    "name": "Snake Skin Photo Cake",
    "url": "https://www.bakerdays.com/snake-skin-photo-cake"
  },
  {
    "name": "Zebra Photo Cake",
    "url": "https://www.bakerdays.com/zebra-photo-cake"
  },
  {
    "name": "Tiger Photo Cake",
    "url": "https://www.bakerdays.com/tiger-photo-cake"
  },
  {
    "name": "Leopard Photo Cake",
    "url": "https://www.bakerdays.com/leopard-photo-cake"
  },
  {
    "name": "Cute Blue Cake",
    "url": "https://www.bakerdays.com/cute-blue-cake"
  },
  {
    "name": "Make Me Happy Cake",
    "url": "https://www.bakerdays.com/make-me-happy-cake"
  },
  {
    "name": "Awesome Photo Cake",
    "url": "https://www.bakerdays.com/awesome-photo-cake"
  },
  {
    "name": "Comic Thoughts Cake",
    "url": "https://www.bakerdays.com/comic-thoughts-cake"
  },
  {
    "name": "Thinking of You Cake",
    "url": "https://www.bakerdays.com/thinking-of-you-cake"
  },
  {
    "name": "Watercolour Thoughts Cake",
    "url": "https://www.bakerdays.com/watercolour-thoughts-cake"
  },
  {
    "name": "You Are Wonderful Cake",
    "url": "https://www.bakerdays.com/you-are-wonderful-cake"
  },
  {
    "name": "Blooming Photo Cake",
    "url": "https://www.bakerdays.com/blooming-photo-cake"
  },
  {
    "name": "Thoughtful Flowers Photo Cake",
    "url": "https://www.bakerdays.com/thoughtful-flowers-photo-cake"
  },
  {
    "name": "Thoughtful Flowers Cake",
    "url": "https://www.bakerdays.com/thoughtful-flowers-cake"
  },
  {
    "name": "Butterfly Cup Gift Set",
    "url": "https://www.bakerdays.com/butterfly-cup-gift-set"
  },
  {
    "name": "Unicorn Love Gift Set",
    "url": "https://www.bakerdays.com/unicorn-love-gift-set"
  },
  {
    "name": "Flamingo Loves You Gift Set",
    "url": "https://www.bakerdays.com/flamingo-love-gift-set"
  },
  {
    "name": "Kiss & Hug Gift Set",
    "url": "https://www.bakerdays.com/kiss-and-hug-gift-set"
  },
  {
    "name": "Love Cup Gift Set",
    "url": "https://www.bakerdays.com/love-cup-gift-set"
  },
  {
    "name": "Puggin' Love Gift Set",
    "url": "https://www.bakerdays.com/puggin-love-gift-set"
  },
  {
    "name": "Excitable Edgar Cake",
    "url": "https://www.bakerdays.com/excitable-edgar-cake"
  }
]